[
    {
  
     "image_url": "https://raw.githubusercontent.com/vrsstudio/img/ab6fdb6fed1d1e279c2195eb65250a4ffd5840a6/crediton.png",
 "rating": 5,
   "obran":"5 (9813 голосів)",
  "sum_one": "300 грн",
  "sum_max": "від 300 - 15000 грн",
  "term_to": "61",
"term_max": "від 61 днів до 180 днів",
    "koszt": "0,01 грн",
     "url": "https://www.google.com.ua/"

        
  
    },
    {
  
     "image_url": "https://raw.githubusercontent.com/vrsstudio/img/ab6fdb6fed1d1e279c2195eb65250a4ffd5840a6/Cashbro.png",
    "rating": 5,
     "obran":"4.9 (5679 голосів)",
    "sum_one": "300 грн",
  "sum_max": "від 300 - 15000 грн",
  "term_to": "61",
"term_max": "від 61 днів до 180 днів",
  "koszt": "0,01 грн",
   "url": "https://www.google.com.ua/"
  
    },

    {
  
     "image_url": "https://raw.githubusercontent.com/vrsstudio/img/ab6fdb6fed1d1e279c2195eb65250a4ffd5840a6/freezlpl.png",
    "rating": 5,
     "obran":"5 (4632 голосів)",
    "sum_one": "100 грн",
  "sum_max": "від 400 - 15000 грн",
  "term_to": "61",
"term_max": "від 61 днів до 180 днів",
  "koszt": "0,01 грн",
   "url": "https://www.google.com.ua/"
  
    },
    {
  
     "image_url": "https://raw.githubusercontent.com/vrsstudio/img/ab6fdb6fed1d1e279c2195eb65250a4ffd5840a6/kuki.png",
    "rating": 5,
     "obran":"5 (8670 голосів)",
    "sum_one": "500 грн",
  "sum_max": "від 500 - 15000 грн",
  "term_to": "61",
"term_max": "від 61 днів до 180 днів",
  "koszt": "0,01 грн",
   "url": "https://www.google.com.ua/"
  
    }
    ,{
  
     "image_url": "https://raw.githubusercontent.com/vrsstudio/img/ab6fdb6fed1d1e279c2195eb65250a4ffd5840a6/Foros.png",
   "rating": 5,
     "obran":"5 (7606 голосів)",
  "sum_one": "500 грн",
  "sum_max": "od 500 - 15000 грн",
  "term_to": "61",
"term_max": "від 61 днів до 180 днів",
"koszt": "0,01 грн",
     "url": "https://www.google.com.ua/"
  
    },
    {
  
     "image_url": "https://raw.githubusercontent.com/vrsstudio/img/ab6fdb6fed1d1e279c2195eb65250a4ffd5840a6/kreditzen.png",
    "rating": 5,
     "obran":"4.7 (3543 голосів)",
    "sum_one": "300 грн",
  "sum_max": "від 300 - 10000 грн",
  "term_to": "61",
"term_max": "від 61 днів до 180 днів",
  "koszt": "0,01 грн",
   "url": "https://www.google.com.ua/"
  
    } ,
    {
  
     "image_url": "https://raw.githubusercontent.com/vrsstudio/img/ab6fdb6fed1d1e279c2195eb65250a4ffd5840a6/cwilivkipl.png",
    "rating": 5,
     "obran":"4.5 (6656 голосів)",
    "sum_one": "50 грн",
  "sum_max": "від 50 - 2000 грн",
  "term_to": "61",
"term_max": "від 61 днів до 180 днів",
  "koszt": "0,01 грн",
   "url": "https://www.google.com.ua/"
  
    },
    {
  
     "image_url": "https://raw.githubusercontent.com/vrsstudio/img/ab6fdb6fed1d1e279c2195eb65250a4ffd5840a6/lendon.png",
    "rating": 5,
     "obran":"4.5 (5122 голосів)",
    "sum_one": "500 грн",
  "sum_max": "від 500 - 7500 грн",
  "term_to": "61",
"term_max": "від 61 днів до 180 днів",
  "koszt": "0,01 грн",
   "url": "https://www.google.com.ua/"
  
    },
    {
  
     "image_url": "https://raw.githubusercontent.com/vrsstudio/img/ab6fdb6fed1d1e279c2195eb65250a4ffd5840a6/netcredpl.png",
     "rating": 5,
       "obran":"4.7 (4345 голосів)",
     "sum_one": "100 грн",
  "sum_max": "від 100 - 5000 грн",
"term_to": "61",
"term_max": "від 61 днів до 180 днів",
  "koszt": "0,01 грн",
     "url": "https://www.google.com.ua/"
        
  
    }   
      
]
